radarly/__init__.py
radarly/analytics.py
radarly/api.py
radarly/auth.py
radarly/benchmark.py
radarly/cloud.py
radarly/cluster.py
radarly/constants.py
radarly/corpus.py
radarly/dashboard.py
radarly/distribution.py
radarly/exceptions.py
radarly/focus.py
radarly/geogrid.py
radarly/influencer.py
radarly/localization.py
radarly/metadata.py
radarly/milestone.py
radarly/model.py
radarly/pivottable.py
radarly/project.py
radarly/publication.py
radarly/rate.py
radarly/socialaccount.py
radarly/socialperformance.py
radarly/tag.py
radarly/topic.py
radarly/user.py
radarly/assets/categories.json
radarly/parameters/__init__.py
radarly/parameters/field.py
radarly/utils/__init__.py
radarly/utils/_internal.py
radarly/utils/checker.py
radarly/utils/colorizer.py
radarly/utils/jsonparser.py
radarly/utils/misc.py
radarly/utils/path.py
radarly/utils/router.py
radarly_py-1.0.17.dist-info/LICENSE
radarly_py-1.0.17.dist-info/METADATA
radarly_py-1.0.17.dist-info/WHEEL
radarly_py-1.0.17.dist-info/top_level.txt
radarly_py-1.0.17.dist-info/RECORD
