Metadata-Version: 2.1
Name: radarly-py
Version: 1.0.17
Summary: Python client for Radarly API
Author: Linkfluence
Author-email: help@linkfluence.com
License: Apache-2.0
Project-URL: Documentation, https://api.linkfluence.com
Keywords: radarly linkfluence api
Classifier: Programming Language :: Python :: 3
Classifier: Programming Language :: Python :: 3.4
Classifier: Programming Language :: Python :: 3.5
Classifier: Programming Language :: Python :: 3.6
Classifier: Programming Language :: Python :: 3.7
Requires-Python: >=3.4
License-File: LICENSE
Requires-Dist: requests
Requires-Dist: lxml
Requires-Dist: pytz
Requires-Dist: python-dateutil
Requires-Dist: pycountry
